sage/__init__.pyc
sage/__pycache__/__init__.cpython-310.pyc
sage/__pycache__/__init__.cpython-311.pyc
sage/kernel/__init__.pyc
sage/kernel/__pycache__/__init__.cpython-310.pyc
sage/kernel/__pycache__/__init__.cpython-311.pyc
sage/kernel/enterprise/__init__.pyc
sage/kernel/enterprise/sage_queue/__init__.pyc
sage/kernel/enterprise/sage_queue/python/__init__.pyc
sage/kernel/enterprise/sage_queue/python/cleanup.pyc
sage/kernel/enterprise/sage_queue/python/debug_queue.pyc
sage/kernel/enterprise/sage_queue/python/sage_demo.pyc
sage/kernel/enterprise/sage_queue/python/sage_queue.pyc
sage/kernel/enterprise/sage_queue/python/sage_queue_manager.pyc
sage/kernel/enterprise/sage_queue/tests/__init__.py
sage/kernel/enterprise/sage_queue/tests/conftest.py
sage/kernel/enterprise/sage_queue/tests/migrate.py
sage/kernel/enterprise/sage_queue/tests/mock_sage_queue.py
sage/kernel/enterprise/sage_queue/tests/run_all_tests.py
sage/kernel/enterprise/sage_queue/tests/run_tests.py
sage/kernel/enterprise/sage_queue/tests/test_basic_functionality.py
sage/kernel/enterprise/sage_queue/tests/test_comprehensive.py
sage/kernel/enterprise/sage_queue/tests/test_multiprocess_concurrent.py
sage/kernel/enterprise/sage_queue/tests/test_performance_benchmark.py
sage/kernel/enterprise/sage_queue/tests/test_queue_functionality.py
sage/kernel/enterprise/sage_queue/tests/test_quick_validation.py
sage/kernel/enterprise/sage_queue/tests/test_ray_integration.py
sage/kernel/enterprise/sage_queue/tests/test_safety.py
sage/kernel/enterprise/sage_queue/tests/validate_test_setup.py
sage/kernel/enterprise/sage_queue/tests/__pycache__/__init__.cpython-311.opt-2.pyc
sage/kernel/enterprise/sage_queue/tests/__pycache__/__init__.cpython-311.pyc
sage/kernel/enterprise/sage_queue/tests/__pycache__/conftest.cpython-311.opt-2.pyc
sage/kernel/enterprise/sage_queue/tests/__pycache__/conftest.cpython-311.pyc
sage/kernel/enterprise/sage_queue/tests/__pycache__/migrate.cpython-311.opt-2.pyc
intellistream_sage_kernel-0.1.6.dist-info/METADATA
intellistream_sage_kernel-0.1.6.dist-info/WHEEL
intellistream_sage_kernel-0.1.6.dist-info/entry_points.txt
intellistream_sage_kernel-0.1.6.dist-info/top_level.txt
intellistream_sage_kernel-0.1.6.dist-info/RECORD
